slav neural/full_adder.v
module full_adder(
    input a, b, cin,
    output sum, cout
);
    assign sum = a ^ b ^ cin;
    assign cout = (a & b) | (cin & (a ^ b));
endmodule

slav neural/output.vcd
$date
	Fri Apr 25 14:19:27 2025
$end
$version
	ModelSim Version 10.5b
$end
$timescale
	1ps
$end

$scope module full_adder $end
$var wire 1 ! a $end
$var wire 1 " b $end
$var wire 1 # cin $end
$var wire 1 $ sum $end
$var wire 1 % cout $end
$upscope $end
$enddefinitions $end
#0
$dumpvars
0!
0"
0#
0$
0%
$end
#10000
1!
1$
#20000
1"
0!
#30000
1!
0$
1%
#40000
1#
0"
0!
0%
1$
#50000
1!
0$
1%
#60000
1"
0!
#70000
1!
1$
#80000
0#
0"
0!
0%
0$
#90000
1!
1$
#100000
1"
0!
#110000
1!
0$
1%
#120000
1#
0"
0!
0%
1$
#130000
1!
0$
1%
#140000
1"
0!
#150000
1!
1$
#160000
0#
0"
0!
0%
0$
#170000
1!
1$
#180000
1"
0!
#190000
1!
0$
1%
#200000
1#
0"
0!
0%
1$
